gita/__init__.py
gita/cli.py
gita/commit.py
gita/git_helper.py
kumosense_gita-1.0.3.dist-info/METADATA
kumosense_gita-1.0.3.dist-info/WHEEL
kumosense_gita-1.0.3.dist-info/entry_points.txt
kumosense_gita-1.0.3.dist-info/top_level.txt
kumosense_gita-1.0.3.dist-info/RECORD
