Metadata-Version: 2.2
Name: kumosense-gita
Version: 1.0.3
Summary: Gita - AI yordamida avtomatik commit yozish CLI
Home-page: https://github.com/Muhiddin0/gita-commit
Author: Sizning Ismingiz
Author-email: contact@muhiddindev.uz
Classifier: Programming Language :: Python :: 3
Classifier: License :: OSI Approved :: MIT License
Classifier: Operating System :: OS Independent
Requires-Python: >=3.7
Requires-Dist: click==8.1.8
Requires-Dist: GitPython==3.1.44
Requires-Dist: g4f==0.4.8.0
Dynamic: author
Dynamic: author-email
Dynamic: classifier
Dynamic: description
Dynamic: description-content-type
Dynamic: home-page
Dynamic: requires-dist
Dynamic: requires-python
Dynamic: summary
